jk_simplexml/EnumTextTrimMode.py
jk_simplexml/EnumWhiteSpaceProcessing.py
jk_simplexml/EnumXMLPrintStyle.py
jk_simplexml/EnumXMLTextOutputEncoding.py
jk_simplexml/HAbstractElement.py
jk_simplexml/HAttribute.py
jk_simplexml/HAttributeList.py
jk_simplexml/HComment.py
jk_simplexml/HElement_HAbstractElementList.py
jk_simplexml/HSerializer.py
jk_simplexml/HText.py
jk_simplexml/HToolkit_Load_HTML.py.DEACTIVATED
jk_simplexml/HToolkit_Load_XML.py.DEACTIVATED
jk_simplexml/ImplementationErrorException.py
jk_simplexml/XMLWriteSettings.py
jk_simplexml/__init__.py
jk_simplexml/impl/HToolkit_Write_Dump.py
jk_simplexml/impl/HToolkit_Write_HTML.py
jk_simplexml/impl/HToolkit_Write_PlainText.py
jk_simplexml/impl/HToolkit_Write_XML.py
jk_simplexml/impl/_CompiledColorSchema.py
jk_simplexml/impl/__init__.py
jk_simplexml-0.2026.1.24.dist-info/licenses/LICENSE.txt
jk_simplexml-0.2026.1.24.dist-info/WHEEL
jk_simplexml-0.2026.1.24.dist-info/METADATA
jk_simplexml-0.2026.1.24.dist-info/RECORD
